crosscompute_printers_pdf/__init__.py
crosscompute_printers_pdf/scripts/print.js
crosscompute_printers_pdf-0.4.1.dist-info/LICENSE.md
crosscompute_printers_pdf-0.4.1.dist-info/METADATA
crosscompute_printers_pdf-0.4.1.dist-info/WHEEL
crosscompute_printers_pdf-0.4.1.dist-info/entry_points.txt
crosscompute_printers_pdf-0.4.1.dist-info/top_level.txt
crosscompute_printers_pdf-0.4.1.dist-info/zip-safe
crosscompute_printers_pdf-0.4.1.dist-info/RECORD
