Metadata-Version: 2.1
Name: crosscompute-printers-pdf
Version: 0.4.1
Summary: Print your automations in PDF format.
Home-page: https://crosscompute.com
Author: CrossCompute Inc.
Author-email: support@crosscompute.com
License: MIT
Project-URL: Bug Tracker, https://github.com/crosscompute/crosscompute-printers-pdf/issues
Project-URL: Documentation, https://github.com/crosscompute/crosscompute-printers-pdf
Project-URL: Source Code, https://github.com/crosscompute/crosscompute-printers-pdf
Platform: any
Classifier: Development Status :: 3 - Alpha
Classifier: Intended Audience :: Developers
Classifier: Intended Audience :: Information Technology
Classifier: Intended Audience :: Science/Research
Classifier: Intended Audience :: System Administrators
Classifier: License :: OSI Approved :: MIT License
Classifier: Operating System :: OS Independent
Classifier: Programming Language :: Python :: 3
Requires-Python: >=3.10
License-File: LICENSE.md
Requires-Dist: crosscompute (>=0.9.4)
Provides-Extra: test
Requires-Dist: pytest-cov ; extra == 'test'
